hf_extractor/__init__.py
hf_extractor/config.py
hf_extractor/extraction/__init__.py
hf_extractor/extraction/extractor.py
hf_extractor/extraction/progress_manager.py
hf_extractor/main/__init__.py
hf_extractor/main/routes.py
hf_extractor/templates/index.html
hf_extractor/tests/conftest.py
hf_extractor/tests/test_pipeline_fake.py
hf_extractor/utils/__init__.py
hf_extractor/utils/logger.py
hf_extractor/utils/schema_generator.py
face_miner-1.0.0.dist-info/METADATA
face_miner-1.0.0.dist-info/WHEEL
face_miner-1.0.0.dist-info/licenses/LICENSE
face_miner-1.0.0.dist-info/RECORD
