Metadata-Version: 2.4
Name: face-miner
Version: 1.0.0
Summary: Extractor for HuggingFace models
Project-URL: Homepage, https://github.com/F201
Project-URL: Issues, https://github.com/F201/hf-extractor
Author-email: "Jati H. Husen" <jatihusen@telkomuniversity.ac.id>, Adam Rafif Faqih <adamrafif@student.telkomuniversity.ac.id>, "M. Daffa Raygama" <daffraygama@student.telkomuniversity.ac.id>, Yanwar Ardika Cahyani <yanwardika@student.telkomuniversity.ac.id>, Farah <farah@student.telkomuniversity.ac.id>
License: MIT License
License-File: LICENSE
Keywords: extractor,huggingface,library
Classifier: Framework :: Flask
Classifier: License :: OSI Approved :: MIT License
Classifier: Operating System :: OS Independent
Classifier: Programming Language :: Python :: 3
Requires-Python: >=3.9
Requires-Dist: flask
Requires-Dist: huggingface-hub
Requires-Dist: pandas
Requires-Dist: requests
